abcweaver/__init__.py
abcweaver/__main__.py
abcweaver/cli.py
abcweaver/commands/__init__.py
abcweaver/core/__init__.py
abcweaver/core/abc_parser.py
abcweaver/core/converter.py
abcweaver/core/musicxml_handler.py
abcweaver/core/validator.py
abcweaver/streams/__init__.py
abcweaver/utils/__init__.py
abcweaver/utils/constants.py
abcweaver/utils/exceptions.py
abcweaver/utils/helpers.py
abcweaver-0.2.1.dist-info/licenses/LICENSE
tests/__init__.py
tests/test_duration_calculations.py
abcweaver-0.2.1.dist-info/METADATA
abcweaver-0.2.1.dist-info/WHEEL
abcweaver-0.2.1.dist-info/entry_points.txt
abcweaver-0.2.1.dist-info/top_level.txt
abcweaver-0.2.1.dist-info/RECORD
