Metadata-Version: 2.4
Name: abcweaver
Version: 0.2.1
Summary: 🎼 ABC ↔ MusicXML Transformation Engine with Redis Stream Processing
Home-page: https://github.com/gerico1007/abcweaver
Author: Gerico1007
Author-email: Gerico1007 <gerico@jgwill.com>
License: MIT
Project-URL: Homepage, https://github.com/gerico1007/abcweaver
Project-URL: Repository, https://github.com/gerico1007/abcweaver.git
Project-URL: Issues, https://github.com/gerico1007/abcweaver/issues
Keywords: music,abc,musicxml,redis,streams,notation
Classifier: Development Status :: 3 - Alpha
Classifier: Intended Audience :: Developers
Classifier: Topic :: Multimedia :: Sound/Audio :: MIDI
Classifier: License :: OSI Approved :: MIT License
Classifier: Programming Language :: Python :: 3
Classifier: Programming Language :: Python :: 3.8
Classifier: Programming Language :: Python :: 3.9
Classifier: Programming Language :: Python :: 3.10
Classifier: Programming Language :: Python :: 3.11
Classifier: Programming Language :: Python :: 3.12
Requires-Python: >=3.8
License-File: LICENSE
Requires-Dist: click>=8.0.0
Requires-Dist: lxml>=4.9.0
Requires-Dist: nyro>=0.1.3
Requires-Dist: pydantic>=2.0.0
Requires-Dist: rich>=13.0.0
Provides-Extra: dev
Requires-Dist: pytest>=7.0.0; extra == "dev"
Requires-Dist: pytest-cov>=4.0.0; extra == "dev"
Requires-Dist: black>=23.0.0; extra == "dev"
Requires-Dist: flake8>=6.0.0; extra == "dev"
Dynamic: author
Dynamic: home-page
Dynamic: license-file
Dynamic: requires-python
